<?xml version="1.0" encoding="UTF-8" ?>
<!DOCTYPE ldml SYSTEM "http://www.unicode.org/cldr/dtd/1.4/ldml.dtd">
<ldml>
	<identity>
		<version number="$Revision: 1.39 $"/>
		<generation date="$Date: 2006/06/24 23:27:01 $"/>
		<language type="so"/>
		<territory type="DJ"/>
	</identity>
	<numbers>
		<currencyFormats>
			<currencyFormatLength>
				<currencyFormat>
					<pattern>¤#,##0.00</pattern>
				</currencyFormat>
			</currencyFormatLength>
		</currencyFormats>
		<currencies>
			<currency type="DJF">
				<symbol>$</symbol>
			</currency>
			<currency type="USD">
				<symbol>US$</symbol>
			</currency>
		</currencies>
	</numbers>
</ldml>
